deepsearchai/__init__.py
deepsearchai/app.py
deepsearchai/embedding_models/__init__.py
deepsearchai/embedding_models/base.py
deepsearchai/embedding_models/blip_image_captioning.py
deepsearchai/embedding_models/clip.py
deepsearchai/embedding_models/whisper_model.py
deepsearchai/embedding_models/whisper_openai.py
deepsearchai/embedding_models_config.py
deepsearchai/enums.py
deepsearchai/llms/__init__.py
deepsearchai/llms/base.py
deepsearchai/llms/configs/__init__.py
deepsearchai/llms/configs/base.py
deepsearchai/llms/configs/openai.py
deepsearchai/llms/openai.py
deepsearchai/sources/__init__.py
deepsearchai/sources/base.py
deepsearchai/sources/data_source.py
deepsearchai/sources/local.py
deepsearchai/sources/s3.py
deepsearchai/sources/utils.py
deepsearchai/sources/youtube.py
deepsearchai/streamlit_app.py
deepsearchai/tests/__init__.py
deepsearchai/tests/end_to_end/add_and_query_chromadb.py
deepsearchai/tests/llms/__init__.py
deepsearchai/tests/llms/test_whisper.py
deepsearchai/tests/sources/FILE_NAME
deepsearchai/tests/sources/__init__.py
deepsearchai/tests/sources/test123
deepsearchai/tests/sources/test_local.py
deepsearchai/tests/sources/test_s3.py
deepsearchai/tests/vector_databases/__init__.py
deepsearchai/tests/vector_databases/test_chromadb.py
deepsearchai/types.py
deepsearchai/utils.py
deepsearchai/vector_databases/__init__.py
deepsearchai/vector_databases/base.py
deepsearchai/vector_databases/chromadb.py
deepsearchai/vector_databases/configs/__init__.py
deepsearchai/vector_databases/configs/base.py
deepsearchai/vector_databases/configs/chromadb.py
deepsearchai-0.3.4.dist-info/LICENSE
deepsearchai-0.3.4.dist-info/METADATA
deepsearchai-0.3.4.dist-info/WHEEL
deepsearchai-0.3.4.dist-info/RECORD
