Metadata-Version: 2.1
Name: deepsearchai
Version: 0.3.4
Summary: 
Author: RupeshBansal
Requires-Python: >=3.9, !=2.7.*, !=3.0.*, !=3.1.*, !=3.2.*, !=3.3.*, !=3.4.*, !=3.5.*, !=3.6.*, !=3.7.*, !=3.8.*, !=3.12.*
Classifier: Programming Language :: Python :: 3
Classifier: Programming Language :: Python :: 3.9
Classifier: Programming Language :: Python :: 3.10
Classifier: Programming Language :: Python :: 3.11
Provides-Extra: audio
Provides-Extra: documentation
Provides-Extra: ui
Provides-Extra: video
Requires-Dist: boto3 (>=1.28.72,<2.0.0)
Requires-Dist: chromadb (>=0.4.15,<0.5.0)
Requires-Dist: ftfy (>=6.1.1,<7.0.0)
Requires-Dist: google-api-python-client (>=2.107.0,<3.0.0) ; extra == "video"
Requires-Dist: langchain (>=0.0.330,<0.0.331)
Requires-Dist: mimetype (>=0.1.5,<0.2.0)
Requires-Dist: openai (>=0.28.1,<0.29.0)
Requires-Dist: openai-whisper (>=20231106,<20231107) ; extra == "audio" or extra == "video"
Requires-Dist: pillow (==10.0.1)
Requires-Dist: pydub (>=0.25.1,<0.26.0)
Requires-Dist: pytube (>=15.0.0,<16.0.0) ; extra == "video"
Requires-Dist: regex (==2023.8.8)
Requires-Dist: sentence-transformers (>=2.2.2,<3.0.0)
Requires-Dist: sphinx (>=7.2.6,<8.0.0) ; extra == "documentation"
Requires-Dist: sphinx-rtd-theme (>=1.3.0,<2.0.0) ; extra == "documentation"
Requires-Dist: streamlit (>=1.28.0,<2.0.0) ; extra == "ui"
Requires-Dist: torch (>=2.0.0,<3.0.0)
Requires-Dist: torchvision (>=0.15.1,!=0.15.2)
